{
  "staff": [
    {
      "userId": "u1",
      "jobTitleName": "Developer",
      "firstName": "King",
      "lastName": "Dav",
      "preferredFullName": "Dav King",
      "staffID": "E1",
      "salary": "112.000",
      "region": "CA",
      "phoneNumber": "408-345-2212",
      "emailAddress": "dav@gmail.com"
    },
    {
      "userId": "u2",
      "jobTitleName": "Developer",
      "firstName": "Sara",
      "lastName": "Eyu",
      "preferredFullName": "Sara Eyu",
      "staffID": "E2",
      "salary": "130.000",
      "region": "CA",
      "phoneNumber": "408-778-3639",
      "emailAddress": "sara@gmail.com"
    },
    {
      "userId": "u3",
      "jobTitleName": "Program analyist",
      "firstName": "Semere",
      "lastName": "Tomas",
      "preferredFullName": "Semere Tomas",
      "staffID": "E3",
      "salary": "95.000",
      "region": "CA",
      "phoneNumber": "408-342-2324",
      "emailAddress": "semere@gmail.com"
    },
    {
      "userId": "u4",
      "jobTitleName": "Network analyist",
      "firstName": "Hellen",
      "lastName": "Daniel",
      "preferredFullName": "Hellen Dnaiel",
      "staffID": "E4",
      "salary": "160.000",
      "region": "AB",
      "phoneNumber": "408-342-9004",
      "emailAddress": "hellen@gmail.com"
    },
    {
      "userId": "u5",
      "jobTitleName": "Office Manager",
      "firstName": "Eski",
      "lastName": "Mulegeta",
      "preferredFullName": "Eski Mulegeta",
      "staffID": "E3",
      "salary": "115.000",
      "region": "CA",
      "phoneNumber": "403-322-2394",
      "emailAddress": "eski@gmail.com"
    },
    {
      "userId": "u6",
      "jobTitleName": "Developer",
      "firstName": "Fabio",
      "lastName": "Weck",
      "preferredFullName": "Fabio Weck",
      "staffID": "E5",
      "salary": "120.000",
      "region": "AB",
      "phoneNumber": "403-070-9876",
      "emailAddress": "myself@gmail.com"
    },
    {
      "userId": "u7",
      "jobTitleName": "Witcher",
      "firstName": "Harry",
      "lastName": "Potter",
      "preferredFullName": "Harry Potter",
      "staffID": "E4",
      "salary": "200.000",
      "region": "HW",
      "phoneNumber": "403-453-9123",
      "emailAddress": "harrybother@hotmail.com"
    },
    {
      "userId": "u8",
      "jobTitleName": "Manager",
      "firstName": "Leticia",
      "lastName": "Spiller",
      "preferredFullName": "Leticia Spiller",
      "staffID": "E5",
      "salary": "210.000",
      "region": "ON",
      "phoneNumber": "403-467-6543",
      "emailAddress": "lele@hotmail.com"
    },
    {
      "userId": "u9",
      "jobTitleName": "Database Manager",
      "firstName": "Sonic",
      "lastName": "Hedgehog",
      "preferredFullName": "Sonic The Headgehog",
      "staffID": "E6",
      "salary": "125.000",
      "region": "AK",
      "phoneNumber": "587-201-2200",
      "emailAddress": "sonicfast@gmail.com"
    },
    {
      "userId": "u10",
      "jobTitleName": "Student",
      "firstName": "Leandro",
      "lastName": "Nogueira",
      "preferredFullName": "Leandro Nogueira",
      "staffID": "E7",
      "salary": "250.000",
      "region": "BR",
      "phoneNumber": "587-987-9012",
      "emailAddress": "lele@gmail.com"
    },
    {
      "userId": "u11",
      "jobTitleName": "Student",
      "firstName": "Tom",
      "lastName": "Cruise",
      "preferredFullName": "Tom Cruise",
      "staffID": "E7",
      "salary": "100.000",
      "region": "NY",
      "phoneNumber": "587-896-9812",
      "emailAddress": "tomcruise@hotmail.com"
    },
    {
      "userId": "u12",
      "jobTitleName": "Jr. Developer",
      "firstName": "Fabio",
      "lastName": "Augusto",
      "preferredFullName": "Fabio Augusto",
      "staffID": "E8",
      "salary": "90.000",
      "region": "AB",
      "phoneNumber": "403-123-4321",
      "emailAddress": "faugusto@outlook.com"
    },
    {
      "userId": "u13",
      "jobTitleName": "Senior Developer",
      "firstName": "Hugo",
      "lastName": "Boss",
      "preferredFullName": "Hugo Boss",
      "staffID": "E9",
      "salary": "300.000",
      "region": "AB",
      "phoneNumber": "587-389-0987",
      "emailAddress": "h.boss@hotmail.com"
    },
    {
      "userId": "u14",
      "jobTitleName": "Accountant",
      "firstName": "Rob",
      "lastName": "Robot",
      "preferredFullName": "Rob Robot",
      "staffID": "E10",
      "salary": "30.000",
      "region": "PT",
      "phoneNumber": "403-987-1029",
      "emailAddress": "roomba@bot.com"
    },
    {
      "userId": "u15",
      "jobTitleName": "Manager",
      "firstName": "Sergio",
      "lastName": "Roberto",
      "preferredFullName": "Sergio Roberto",
      "staffID": "E11",
      "salary": "200.000",
      "region": "BR",
      "phoneNumber": "587-899-0981",
      "emailAddress": "sroberto@gmail.com"
    },
    {
      "userId": "u16",
      "jobTitleName": "Network analyist",
      "firstName": "Chris",
      "lastName": "Nolan",
      "preferredFullName": "Chris Nolan",
      "staffID": "E11",
      "salary": "90.000",
      "region": "ON",
      "phoneNumber": "587-091-2345",
      "emailAddress": "c.nolan@gmail.com"
    },
    {
      "userId": "u17",
      "jobTitleName": "Developer",
      "firstName": "Hebe",
      "lastName": "Camargo",
      "preferredFullName": "Hebe Camargo",
      "staffID": "E12",
      "salary": "120.000",
      "region": "AB",
      "phoneNumber": "403-402-4012",
      "emailAddress": "hebesbt@hotmail.com"
    }
  ]
}